odoo9_addon_l10n_br_crm-9.0.1.0.0-py2.7-nspkg.pth
odoo_addons/l10n_br_crm/__openerp__.py
odoo_addons/l10n_br_crm/__init__.py
odoo_addons/l10n_br_crm/README.rst
odoo_addons/l10n_br_crm/models/__init__.py
odoo_addons/l10n_br_crm/models/crm_lead.py
odoo_addons/l10n_br_crm/i18n/pt_BR.po
odoo_addons/l10n_br_crm/test/crm_lead.yml
odoo_addons/l10n_br_crm/views/crm_lead_view.xml
odoo_addons/l10n_br_crm/views/crm_opportunity_view.xml
odoo_addons/l10n_br_crm/static/description/icon.png
odoo9_addon_l10n_br_crm-9.0.1.0.0.dist-info/top_level.txt
odoo9_addon_l10n_br_crm-9.0.1.0.0.dist-info/WHEEL
odoo9_addon_l10n_br_crm-9.0.1.0.0.dist-info/RECORD
odoo9_addon_l10n_br_crm-9.0.1.0.0.dist-info/metadata.json
odoo9_addon_l10n_br_crm-9.0.1.0.0.dist-info/DESCRIPTION.rst
odoo9_addon_l10n_br_crm-9.0.1.0.0.dist-info/METADATA
odoo9_addon_l10n_br_crm-9.0.1.0.0.dist-info/namespace_packages.txt
